syscolouringsaddon/__init__.py
syscolouringsaddon-1.1.0.dist-info/METADATA
syscolouringsaddon-1.1.0.dist-info/WHEEL
syscolouringsaddon-1.1.0.dist-info/top_level.txt
syscolouringsaddon-1.1.0.dist-info/RECORD
