Metadata-Version: 2.1
Name: syscolouringsaddon
Version: 1.1.0
Summary: Usefull utility package
Home-page: UNKNOWN
Author: Josef M
Author-email: johannes.mayer@yahoo.com
License: UNKNOWN
Keywords: python
Platform: UNKNOWN
Classifier: Operating System :: Microsoft :: Windows
